[
  {
    "id": 1,
    "name": "๐ ุญุฐุงุก ุฑูุงุถู",
    "description": "ุฑุงุญุฉ ูุฃูุงูุฉ ููููุฉ",
    "price": 120,
    "image": "https://example.com/shoe1.jpg"
  },
  {
    "id": 2,
    "name": "โ ุณุงุนุฉ ุฌูุฏ ูุงุฎุฑุฉ",
    "description": "ุชุตููู ุฑุงูู ูุนููู",
    "price": 250,
    "image": "https://example.com/watch1.jpg"
  },
  {
    "id": 3,
    "name": "๐ธ ุนุทุฑ ูุฑูุณู",
    "description": "ุฑุงุฆุญุฉ ุฌุฐุงุจุฉ ูุซุงุจุชุฉ",
    "price": 180,
    "image": "https://example.com/perfume.jpg"
  },
  {
    "id": 4,
    "name": "๐ ุญููุจุฉ ูุฏ ูุณุงุฆูุฉ",
    "description": "ุนูููุฉ ูุฃูููุฉ",
    "price": 199,
    "image": "https://example.com/bag.jpg"
  },
  {
    "id": 5,
    "name": "๐ ุญุฐุงุก ุฌูุฏ ุฑุฌุงูู ููุงุณููู",
    "description": "ุฃูุงูุฉ ููููุงุณุจุงุช ุงูุฑุณููุฉ ูุฑุงุญุฉ ููููุฉ.",
    "price": 270,
    "image": "https://example.com/leather-shoe.jpg"
  }
]